{
  "productos": [
    {
      "nombre": "Barcelona",
      "descripcion": "Equipo",      
      "imagen": "https://img.a.transfermarkt.technology/portrait/header/3226-1542113764.jpg?lm=1",
      "id": 1,
      "precio":33.50
    },
    {
      "nombre": "aa",
      "descripcion": "bbb",      
      "imagen": "https://img.a.transfermarkt.technology/portrait/header/3226-1542113764.jpg?lm=1",
      "id": 2,
      "precio":6.50
    },
    {
      "nombre": "asdfasdf",
      "descripcion": "bbbasdfasdf",      
      "imagen": "https://img.a.transfermarkt.technology/portrait/header/3226-1542113764.jpg?lm=1",
      "id": 3,
      "precio":10.90
    },
    {
      "nombre": "fasdfa",
      "descripcion": "basdfabbasdfasdf",      
      "imagen": "https://img.a.transfermarkt.technology/portrait/header/3226-1542113764.jpg?lm=1",
      "id": 4,
      "precio":20.50
    }   
  ]
}